pyricc/__init__.py
pyricc/_version.py
pyricc/colors.py
pyricc-0.1.5.dist-info/LICENSE
pyricc-0.1.5.dist-info/METADATA
pyricc-0.1.5.dist-info/WHEEL
pyricc-0.1.5.dist-info/top_level.txt
pyricc-0.1.5.dist-info/RECORD
