Metadata-Version: 2.2
Name: pyricc
Version: 0.1.5
Summary: A small library for coloring strings.
Author-email: Riccardo Carlesso <pall.adius.bont.on+pyricc@googlemail.com>
License: MIT License
Project-URL: Homepage, https://github.com/palladius/pyricc
Project-URL: Bug Tracker, https://github.com/palladius/pyricc/issues
Classifier: Programming Language :: Python :: 3
Classifier: License :: OSI Approved :: MIT License
Classifier: Operating System :: OS Independent
Requires-Python: >=3.7
License-File: LICENSE
